arcade_trello_api/__init__.py
arcade_trello_api/tools/__init__.py
arcade_trello_api/tools/request_body_schemas.py
arcade_trello_api/wrapper_tools/AddAttachmentToTrelloCard.json
arcade_trello_api/wrapper_tools/AddCommentToTrelloCard.json
arcade_trello_api/wrapper_tools/AddDropdownOptionCustomField.json
arcade_trello_api/wrapper_tools/AddDropdownOptionTrello.json
arcade_trello_api/wrapper_tools/AddLabelToCard.json
arcade_trello_api/wrapper_tools/AddLabelToTrelloCard.json
arcade_trello_api/wrapper_tools/AddMemberToBoard.json
arcade_trello_api/wrapper_tools/AddMemberToTrelloBoard.json
arcade_trello_api/wrapper_tools/AddMemberToTrelloCard.json
arcade_trello_api/wrapper_tools/AddOrUpdateWorkspaceMember.json
arcade_trello_api/wrapper_tools/AddOrganizationsToEnterprise.json
arcade_trello_api/wrapper_tools/AddReactionToTrelloAction.json
arcade_trello_api/wrapper_tools/AddStickerToCard.json
arcade_trello_api/wrapper_tools/AddStickerToTrelloCard.json
arcade_trello_api/wrapper_tools/AddTrelloCardComment.json
arcade_trello_api/wrapper_tools/AddTrelloWebhook.json
arcade_trello_api/wrapper_tools/ArchiveAllCardsInList.json
arcade_trello_api/wrapper_tools/ArchiveOrUnarchiveTrelloList.json
arcade_trello_api/wrapper_tools/ArchiveUnarchiveListTrello.json
arcade_trello_api/wrapper_tools/CheckBoardBillableGuests.json
arcade_trello_api/wrapper_tools/CheckNewBillableGuestsOnBoard.json
arcade_trello_api/wrapper_tools/CheckOrgTransferability.json
arcade_trello_api/wrapper_tools/CheckOrganizationTransferability.json
arcade_trello_api/wrapper_tools/CreateBoardTag.json
arcade_trello_api/wrapper_tools/CreateCheckitemInChecklist.json
arcade_trello_api/wrapper_tools/CreateCheckitemOnChecklist.json
arcade_trello_api/wrapper_tools/CreateChecklistOnCard.json
arcade_trello_api/wrapper_tools/CreateCustomEmoji.json
arcade_trello_api/wrapper_tools/CreateCustomEmojiTrello.json
arcade_trello_api/wrapper_tools/CreateEnterpriseAuthToken.json
arcade_trello_api/wrapper_tools/CreateLabelOnBoard.json
arcade_trello_api-3.0.0.dist-info/METADATA
arcade_trello_api-3.0.0.dist-info/WHEEL
arcade_trello_api-3.0.0.dist-info/entry_points.txt
arcade_trello_api-3.0.0.dist-info/licenses/LICENSE
arcade_trello_api-3.0.0.dist-info/RECORD
